json_numpy/__init__.py
json_numpy/version.py
json_numpy_sebastian_achim_mueller-0.1.9.dist-info/licenses/LICENSE
json_numpy_sebastian_achim_mueller-0.1.9.dist-info/METADATA
json_numpy_sebastian_achim_mueller-0.1.9.dist-info/WHEEL
json_numpy_sebastian_achim_mueller-0.1.9.dist-info/top_level.txt
json_numpy_sebastian_achim_mueller-0.1.9.dist-info/RECORD
